{"cameraMode":{"drawMode":0,"name":"Shaded","section":"Shading Mode"},"sceneLighting":true,"audioPlay":false,"sceneViewState":{"m_AlwaysRefresh":false,"showFog":true,"showSkybox":true,"showFlares":true,"showImageEffects":true,"showParticleSystems":true,"showVisualEffectGraphs":true,"m_FxEnabled":true},"in2DMode":false,"pivot":{"x":3.906773805618286,"y":5.907217979431152,"z":4.600569725036621},"rotation":{"x":0.0686357319355011,"y":-0.9312389492988586,"z":0.24455004930496217,"w":0.2613459527492523},"size":0.10515954345464707,"orthographic":false}